fluidattacks_tracks/__init__.py
fluidattacks_tracks/client.py
fluidattacks_tracks/py.typed
fluidattacks_tracks/utils.py
fluidattacks_tracks/auth/__init__.py
fluidattacks_tracks/auth/base.py
fluidattacks_tracks/auth/iam.py
fluidattacks_tracks/resources/__init__.py
fluidattacks_tracks/resources/event.py
fluidattacks_tracks-0.9.5.dist-info/METADATA
fluidattacks_tracks-0.9.5.dist-info/WHEEL
fluidattacks_tracks-0.9.5.dist-info/RECORD
