Metadata-Version: 2.4
Name: fluidattacks-tracks
Version: 0.9.5
Summary: Python library for usage analytics
Author-email: Fluid Attacks Engineering <development@fluidattacks.com>
License-Expression: MPL-2.0
Requires-Python: <3.14,>=3.11
Requires-Dist: aiohttp>=3.12.15
Requires-Dist: aiolimiter>=1.2.1
Requires-Dist: pydantic>=2.11.7
Requires-Dist: simplejson>=3.20.1
Requires-Dist: tenacity>=9.1.2
Provides-Extra: auth
Requires-Dist: aiobotocore>=2.16.0; extra == 'auth'
